tkgpio/Adafruit_CharLCD.py
tkgpio/__init__.py
tkgpio/base.py
tkgpio/lirc.py
tkgpio/py_irsend/__init__.py
tkgpio/py_irsend/irsend.py
tkgpio/resources/fonts/hd44780.ttf
tkgpio/resources/images/button_pressed.png
tkgpio/resources/images/button_released.png
tkgpio/resources/images/buzzer_off.png
tkgpio/resources/images/buzzer_on.png
tkgpio/resources/images/distance_sensor.png
tkgpio/resources/images/emitter_off.png
tkgpio/resources/images/emitter_on.png
tkgpio/resources/images/led_off.png
tkgpio/resources/images/led_on.png
tkgpio/resources/images/light_sensor.png
tkgpio/resources/images/motion_sensor_off.png
tkgpio/resources/images/motion_sensor_on.png
tkgpio/resources/images/motion_sensor_wait.png
tkgpio/resources/images/motor.png
tkgpio/resources/images/servo_arm.png
tkgpio/resources/images/servo_base.png
tkgpio/tkgpio.py
tkgpio-0.1.2.dist-info/LICENSE
tkgpio-0.1.2.dist-info/METADATA
tkgpio-0.1.2.dist-info/WHEEL
tkgpio-0.1.2.dist-info/RECORD
