Metadata-Version: 2.3
Name: tkgpio
Version: 0.1.2
Summary: A Python library to simulate Raspberry Pi GPIO devices in TkInter
License: MIT
Keywords: raspberrypi,gpio,tkinter
Author: Jan K. S.
Author-email: developer@janks.dev.br
Requires-Python: >=3.5,<4.0
Classifier: Intended Audience :: Developers
Classifier: Intended Audience :: Education
Classifier: License :: OSI Approved :: MIT License
Classifier: Operating System :: OS Independent
Classifier: Programming Language :: Python :: 3
Classifier: Programming Language :: Python :: 3.5
Classifier: Programming Language :: Python :: 3.6
Classifier: Programming Language :: Python :: 3.7
Classifier: Programming Language :: Python :: 3.8
Classifier: Programming Language :: Python :: 3.9
Classifier: Programming Language :: Python :: 3.10
Classifier: Programming Language :: Python :: 3.11
Classifier: Programming Language :: Python :: 3.12
Classifier: Programming Language :: Python :: 3.13
Classifier: Topic :: Education
Classifier: Topic :: System :: Hardware
Provides-Extra: sound
Requires-Dist: Pillow
Requires-Dist: gpiozero (>=1.6.2,<1.7.0)
Requires-Dist: numpy ; extra == "sound"
Requires-Dist: sounddevice ; extra == "sound"
Project-URL: Repository, https://github.com/wallysalami/tkgpio
